setup.py
django_translate/__init__.py
django_translate/middleware.py
django_translate/models.py
django_translate/services.py
django_translate/settings.py
django_translate/utils.py
django_translate.egg-info/PKG-INFO
django_translate.egg-info/SOURCES.txt
django_translate.egg-info/dependency_links.txt
django_translate.egg-info/pbr.json
django_translate.egg-info/requires.txt
django_translate.egg-info/top_level.txt
django_translate/extractors/__init__.py
django_translate/extractors/django_template.py
django_translate/management/__init__.py
django_translate/management/commands/__init__.py
django_translate/management/commands/tranzdump.py
django_translate/management/commands/tranzvalidate.py
django_translate/templatetags/__init__.py
django_translate/templatetags/tranz.py