Metadata-Version: 1.0
Name: django-translate
Version: 1.0.14
Summary: Non-gettext translations for django.
Home-page: https://github.com/adamziel/django_translate
Author: Adam Zieliński
Author-email: adam@sf2.guru
License: MIT
Platform: UNKNOWN
